cro/__init__.py
cro/_init_.py
cro/cro.py
cro/fitness.py
cro/larvaemutation.py
cro/reef_initialization.py
cro/report.py
cro/utils.py
cro-0.0.5.2.dist-info/LICENSE.txt
cro-0.0.5.2.dist-info/METADATA
cro-0.0.5.2.dist-info/WHEEL
cro-0.0.5.2.dist-info/top_level.txt
cro-0.0.5.2.dist-info/RECORD
